arpoc/__init__.py
arpoc/__main__.py
arpoc/base.py
arpoc/cache.py
arpoc/config.py
arpoc/exceptions.py
arpoc/mypy.ini
arpoc/special_pages.py
arpoc/utils.py
arpoc/ac/__init__.py
arpoc/ac/__main__.py
arpoc/ac/common.py
arpoc/ac/conflict_resolution.py
arpoc/ac/lark_adapter.py
arpoc/ac/parser.py
arpoc/pap/__init__.py
arpoc/pap/resources/__init__.py
arpoc/pap/resources/templates/pap.html
arpoc/pap/resources/templates/testbed.html
arpoc/plugins/.obl_loggers.py.swp
arpoc/plugins/__init__.py
arpoc/plugins/_lib.py
arpoc/plugins/env_attr_time.py
arpoc/plugins/obj_json.py
arpoc/plugins/obj_urlmap.py
arpoc/plugins/obl_loggers.py
arpoc/resources/__init__.py
arpoc/resources/config.yml
arpoc/resources/grammar.lark
arpoc/resources/loggers.yml
arpoc/resources/templates/500.html
arpoc/resources/templates/auth.html
arpoc/resources/templates/userinfo.html
ARPOC-0.3.1.dist-info/LICENSE
ARPOC-0.3.1.dist-info/METADATA
ARPOC-0.3.1.dist-info/WHEEL
ARPOC-0.3.1.dist-info/entry_points.txt
ARPOC-0.3.1.dist-info/top_level.txt
ARPOC-0.3.1.dist-info/RECORD
